alpfore/__init__.py
alpfore/candidate_selectors/__init__.py
alpfore/candidate_selectors/thompson_sampling.py
alpfore/cli.py
alpfore/core/__init__.py
alpfore/core/candidate_selector.py
alpfore/core/evaluator.py
alpfore/core/loader.py
alpfore/core/model.py
alpfore/core/trajectory_interface.py
alpfore/encoder/__init__.py
alpfore/encoder/system_encoder.py
alpfore/evaluators/__init__.py
alpfore/evaluators/ddG.py
alpfore/evaluators/dna_hybridization.py
alpfore/loaders/__init__.py
alpfore/loaders/colvar_loader.py
alpfore/loaders/lammps_loader.py
alpfore/models/__init__.py
alpfore/models/gp_model.py
alpfore/models/kernels.py
alpfore/models/trainer.py
alpfore/pipeline/__init__.py
alpfore/pipeline/pipeline.py
alpfore/trajectories/__init__.py
alpfore/trajectories/colvar_trajectory.py
alpfore/trajectories/lammps_trajectory.py
alpfore/utils/__init__.py
alpfore/utils/dataset_utils.py
alpfore/utils/kernel_utils.py
alpfore-0.1.6.dist-info/METADATA
alpfore-0.1.6.dist-info/WHEEL
alpfore-0.1.6.dist-info/entry_points.txt
alpfore-0.1.6.dist-info/RECORD
