Metadata-Version: 2.1
Name: alpfore
Version: 0.1.6
Summary: Active Learning Pipeline For Optimal Ranking Estimation
Home-page: https://github.com/nherringer/ALPineFOREst
License: MIT
Keywords: active learning,molecular simulation,machine learning
Author: Nicholas Herringer
Author-email: nherringer@uchicago.edu
Requires-Python: >=3.7,<4.0
Classifier: License :: OSI Approved :: MIT License
Classifier: Operating System :: OS Independent
Classifier: Programming Language :: Python :: 3
Classifier: Programming Language :: Python :: 3.7
Classifier: Programming Language :: Python :: 3.8
Classifier: Programming Language :: Python :: 3.9
Classifier: Programming Language :: Python :: 3.10
Classifier: Programming Language :: Python :: 3.11
Project-URL: Repository, https://github.com/nherringer/ALPineFOREst
